package_uploader/__init__.py
package_uploader/__main__.py
package_uploader/conf.py
package_uploader/exceptions.py
package_uploader/log_utils.py
package_uploader/package_file.py
package_uploader/uploaders/__init__.py
package_uploader/uploaders/base.py
package_uploader/uploaders/ssh_pypi.py
package_uploader-1.0.1.dist-info/LICENSE.txt
package_uploader-1.0.1.dist-info/METADATA
package_uploader-1.0.1.dist-info/WHEEL
package_uploader-1.0.1.dist-info/entry_points.txt
package_uploader-1.0.1.dist-info/top_level.txt
package_uploader-1.0.1.dist-info/RECORD
