Metadata-Version: 2.1
Name: package-uploader
Version: 1.0.1
Summary: Python Package Uploader - designed to upload your built packages to any non-standard repository
Home-page: https://github.com/gbdlin/package-uploader
Author: GwynBleidD
Author-email: gbd.lin@gmail.com
License: MIT
Keywords: django admin toolbox sidebar tools improvements
Platform: UNKNOWN
Classifier: Development Status :: 2 - Pre-Alpha
Classifier: Environment :: Web Environment
Classifier: Intended Audience :: Developers
Classifier: Intended Audience :: System Administrators
Classifier: License :: OSI Approved :: MIT License
Classifier: Operating System :: OS Independent
Classifier: Programming Language :: Python :: 3 :: Only
Classifier: Programming Language :: Python :: 3
Classifier: Programming Language :: Python :: 3.6
Classifier: Programming Language :: Python :: 3.7
Requires-Python: >=3.6, <4
Requires-Dist: colorama
Requires-Dist: pysftp
Requires-Dist: pyyaml
Requires-Dist: six
